xh1scr.py
xh1scr-1.0.7.dist-info/WHEEL
xh1scr-1.0.7.dist-info/METADATA
xh1scr-1.0.7.dist-info/RECORD
