Metadata-Version: 2.1
Name: xh1scr
Version: 1.0.7
Summary: TikTok Magic API Wrapper
Author: perfecto
Author-email: rektnpc@mail.ru
Requires-Python: >=3.7,<4.0
Classifier: Programming Language :: Python :: 3
Classifier: Programming Language :: Python :: 3.7
Classifier: Programming Language :: Python :: 3.8
Classifier: Programming Language :: Python :: 3.9
Requires-Dist: aiohttp (>=3.7.4,<4.0.0)
Requires-Dist: asyncio (>=3.4.3,<4.0.0)
Requires-Dist: beautifulsoup4 (>=4.9.3,<5.0.0)
